[
  {
    "label": "Nonthaburi, Nonthaburi Province, Thailand",
    "latitude": 13.824084688325192,
    "longitude": 100.46244996646598,
    "aqi": 199.98025107355363
  },
  {
    "label": "Nonthaburi, Nonthaburi Province, Thailand",
    "latitude": 13.896622791869301,
    "longitude": 100.36553627223235,
    "aqi": 156.99134321068112
  },
  {
    "label": "Nonthaburi, Nonthaburi Province, Thailand",
    "latitude": 14.024191464678903,
    "longitude": 100.46379615117996,
    "aqi": 119.75002981816492
  },
  {
    "label": "Nonthaburi, Nonthaburi Province, Thailand",
    "latitude": 13.832696865991572,
    "longitude": 100.53987787034973,
    "aqi": 51.277037496582196
  },
  {
    "label": "Nonthaburi, Nonthaburi Province, Thailand",
    "latitude": 13.834941590833932,
    "longitude": 100.48992910773897,
    "aqi": 84.32749759181951
  },
  {
    "label": "Nonthaburi, Nonthaburi Province, Thailand",
    "latitude": 13.782429072343293,
    "longitude": 100.59827173919048,
    "aqi": 148.20931971145964
  },
  {
    "label": "Nonthaburi, Nonthaburi Province, Thailand",
    "latitude": 13.845549583257545,
    "longitude": 100.46073266239422,
    "aqi": 33.51884827439416
  },
  {
    "label": "Nonthaburi, Nonthaburi Province, Thailand",
    "latitude": 13.813552641587993,
    "longitude": 100.64283186753082,
    "aqi": 202.67850948004084
  },
  {
    "label": "Nonthaburi, Nonthaburi Province, Thailand",
    "latitude": 13.901321141422464,
    "longitude": 100.56812513203789,
    "aqi": 41.36805425264248
  },
  {
    "label": "Nonthaburi, Nonthaburi Province, Thailand",
    "latitude": 13.881051986665486,
    "longitude": 100.50496636159264,
    "aqi": 146.2576996284493
  },
  {
    "label": "Nonthaburi, Nonthaburi Province, Thailand",
    "latitude": 13.727873094172068,
    "longitude": 100.47534324546635,
    "aqi": 71.60898702004903
  },
  {
    "label": "Nonthaburi, Nonthaburi Province, Thailand",
    "latitude": 13.95038447456831,
    "longitude": 100.55583334775385,
    "aqi": 93.46847948685192
  },
  {
    "label": "Nonthaburi, Nonthaburi Province, Thailand",
    "latitude": 13.90592602734009,
    "longitude": 100.46480182260257,
    "aqi": 47.9789096805751
  },
  {
    "label": "Nonthaburi, Nonthaburi Province, Thailand",
    "latitude": 13.997429661279805,
    "longitude": 100.42485577513858,
    "aqi": 113.28983549501957
  },
  {
    "label": "Nonthaburi, Nonthaburi Province, Thailand",
    "latitude": 13.771811810279354,
    "longitude": 100.36705738454408,
    "aqi": 216.73134684327061
  },
  {
    "label": "Nonthaburi, Nonthaburi Province, Thailand",
    "latitude": 13.989533376841173,
    "longitude": 100.53682905364136,
    "aqi": 60.631228886450366
  },
  {
    "label": "Nonthaburi, Nonthaburi Province, Thailand",
    "latitude": 13.798704738662082,
    "longitude": 100.383512466228,
    "aqi": 137.52377918202814
  },
  {
    "label": "Nonthaburi, Nonthaburi Province, Thailand",
    "latitude": 13.874835812435736,
    "longitude": 100.42146145336991,
    "aqi": 44.25830050962179
  },
  {
    "label": "Nonthaburi, Nonthaburi Province, Thailand",
    "latitude": 13.94874709101798,
    "longitude": 100.5275200001789,
    "aqi": 175.22017479004634
  },
  {
    "label": "Nonthaburi, Nonthaburi Province, Thailand",
    "latitude": 13.99083190653285,
    "longitude": 100.49995958566899,
    "aqi": 50.826765681827695
  },
  {
    "label": "Nonthaburi, Nonthaburi Province, Thailand",
    "latitude": 13.727094706307714,
    "longitude": 100.55060737323049,
    "aqi": 137.26744766280632
  },
  {
    "label": "Nonthaburi, Nonthaburi Province, Thailand",
    "latitude": 13.736571642615779,
    "longitude": 100.47332277233065,
    "aqi": 190.34252433623925
  },
  {
    "label": "Nonthaburi, Nonthaburi Province, Thailand",
    "latitude": 13.87943433059106,
    "longitude": 100.39408056841047,
    "aqi": 141.72394222106155
  },
  {
    "label": "Nonthaburi, Nonthaburi Province, Thailand",
    "latitude": 13.773580942986841,
    "longitude": 100.35931528879368,
    "aqi": 113.20375262702663
  },
  {
    "label": "Nonthaburi, Nonthaburi Province, Thailand",
    "latitude": 13.770864891981827,
    "longitude": 100.62521399272295,
    "aqi": 182.65716553459245
  },
  {
    "label": "Nong Khai, Isaan, Thailand",
    "latitude": 17.75678303103296,
    "longitude": 102.8506958742504,
    "aqi": 145.07731824364174
  },
  {
    "label": "Nong Khai, Isaan, Thailand",
    "latitude": 17.8562473802101,
    "longitude": 102.74909267740934,
    "aqi": 122.26249822103827
  },
  {
    "label": "Nong Khai, Isaan, Thailand",
    "latitude": 17.97586556346737,
    "longitude": 102.83859948388317,
    "aqi": 122.61158843195118
  },
  {
    "label": "Nong Khai, Isaan, Thailand",
    "latitude": 17.963246970406995,
    "longitude": 102.85718339199649,
    "aqi": 31.0193370951134
  },
  {
    "label": "Nong Khai, Isaan, Thailand",
    "latitude": 17.875465917496662,
    "longitude": 102.59027618695622,
    "aqi": 138.30727003396842
  },
  {
    "label": "Nong Khai, Isaan, Thailand",
    "latitude": 17.753414499532145,
    "longitude": 102.70300121228921,
    "aqi": 93.15541550163367
  },
  {
    "label": "Nong Khai, Isaan, Thailand",
    "latitude": 17.947194315553464,
    "longitude": 102.91335724073977,
    "aqi": 35.44590355163944
  },
  {
    "label": "Nong Khai, Isaan, Thailand",
    "latitude": 17.939579199710423,
    "longitude": 102.90241271841461,
    "aqi": 108.07953361754639
  },
  {
    "label": "Nong Khai, Isaan, Thailand",
    "latitude": 18.008769531723008,
    "longitude": 102.69042090331753,
    "aqi": 135.95622959520915
  },
  {
    "label": "Nong Khai, Isaan, Thailand",
    "latitude": 17.7955898712276,
    "longitude": 102.87796350092313,
    "aqi": 199.36312364133462
  },
  {
    "label": "Nong Khai, Isaan, Thailand",
    "latitude": 17.972224256948657,
    "longitude": 102.87652839463094,
    "aqi": 201.3023220816845
  },
  {
    "label": "Nong Khai, Isaan, Thailand",
    "latitude": 17.707557360098228,
    "longitude": 102.733828483985,
    "aqi": 29.46952278804014
  },
  {
    "label": "Nong Khai, Isaan, Thailand",
    "latitude": 17.818597930417805,
    "longitude": 102.56879542210909,
    "aqi": 139.429761908523
  },
  {
    "label": "Nong Khai, Isaan, Thailand",
    "latitude": 17.85182251587125,
    "longitude": 102.55565511810786,
    "aqi": 116.81789278367607
  },
  {
    "label": "Nong Khai, Isaan, Thailand",
    "latitude": 17.959063828622796,
    "longitude": 102.65512870674173,
    "aqi": 98.44889307134993
  },
  {
    "label": "Nong Khai, Isaan, Thailand",
    "latitude": 17.702965323038182,
    "longitude": 102.72408461957153,
    "aqi": 170.98847868591085
  },
  {
    "label": "Nong Khai, Isaan, Thailand",
    "latitude": 17.715027700940535,
    "longitude": 102.71093418241306,
    "aqi": 26.93007017393508
  },
  {
    "label": "Nong Khai, Isaan, Thailand",
    "latitude": 17.77821385232433,
    "longitude": 102.88205609924246,
    "aqi": 212.46187752189581
  },
  {
    "label": "Nong Khai, Isaan, Thailand",
    "latitude": 17.9880934143881,
    "longitude": 102.83753798963586,
    "aqi": 83.04498151512226
  },
  {
    "label": "Nong Khai, Isaan, Thailand",
    "latitude": 17.981230687400643,
    "longitude": 102.8952719365068,
    "aqi": 135.43041904004724
  },
  {
    "label": "Nong Khai, Isaan, Thailand",
    "latitude": 18.019503801830698,
    "longitude": 102.64756664134656,
    "aqi": 160.9588611108342
  },
  {
    "label": "Nong Khai, Isaan, Thailand",
    "latitude": 17.872616679233534,
    "longitude": 102.58020187905441,
    "aqi": 128.4153520611988
  },
  {
    "label": "Nong Khai, Isaan, Thailand",
    "latitude": 17.761686599529515,
    "longitude": 102.8057339943296,
    "aqi": 37.39170115381485
  },
  {
    "label": "Nong Khai, Isaan, Thailand",
    "latitude": 17.96897272865587,
    "longitude": 102.83193078944697,
    "aqi": 132.42013149533068
  },
  {
    "label": "Nong Khai, Isaan, Thailand",
    "latitude": 17.800434485572815,
    "longitude": 102.85574395106443,
    "aqi": 80.80809803422693
  },
  {
    "label": "Yasothon, Thailand",
    "latitude": 15.851402097770336,
    "longitude": 104.24240407002164,
    "aqi": 213.48002560706433
  },
  {
    "label": "Yasothon, Thailand",
    "latitude": 15.792279327496853,
    "longitude": 104.25514585919325,
    "aqi": 83.20899991039911
  },
  {
    "label": "Yasothon, Thailand",
    "latitude": 15.66309807188199,
    "longitude": 104.03458405732509,
    "aqi": 116.27317729848946
  },
  {
    "label": "Yasothon, Thailand",
    "latitude": 15.915619523064336,
    "longitude": 104.19738795879384,
    "aqi": 156.44632652203077
  },
  {
    "label": "Yasothon, Thailand",
    "latitude": 15.713350629900042,
    "longitude": 104.10411417850511,
    "aqi": 133.70176669611436
  },
  {
    "label": "Yasothon, Thailand",
    "latitude": 15.72845527354708,
    "longitude": 104.26659147245847,
    "aqi": 50.834456939732476
  },
  {
    "label": "Yasothon, Thailand",
    "latitude": 15.684802521767155,
    "longitude": 104.0073239738256,
    "aqi": 153.23681140862993
  },
  {
    "label": "Yasothon, Thailand",
    "latitude": 15.830397447623906,
    "longitude": 104.29870685087913,
    "aqi": 124.02886906997257
  },
  {
    "label": "Yasothon, Thailand",
    "latitude": 15.808380993917892,
    "longitude": 103.976281909512,
    "aqi": 143.62833992546834
  },
  {
    "label": "Yasothon, Thailand",
    "latitude": 15.95664675652432,
    "longitude": 104.08211937748196,
    "aqi": 165.12210285648482
  },
  {
    "label": "Yasothon, Thailand",
    "latitude": 15.855617672851826,
    "longitude": 104.00196659166076,
    "aqi": 195.97693654193313
  },
  {
    "label": "Yasothon, Thailand",
    "latitude": 15.709586469274393,
    "longitude": 104.21948788429064,
    "aqi": 61.92099577479449
  },
  {
    "label": "Yasothon, Thailand",
    "latitude": 15.792568550262077,
    "longitude": 104.26849297852193,
    "aqi": 115.8668912487914
  },
  {
    "label": "Yasothon, Thailand",
    "latitude": 15.728591207052416,
    "longitude": 104.19255101004966,
    "aqi": 170.16228286447762
  },
  {
    "label": "Yasothon, Thailand",
    "latitude": 15.930409755478081,
    "longitude": 104.1225781932902,
    "aqi": 219.37268083972026
  },
  {
    "label": "Yasothon, Thailand",
    "latitude": 15.944986761474365,
    "longitude": 104.21877692910788,
    "aqi": 43.593818299224665
  },
  {
    "label": "Yasothon, Thailand",
    "latitude": 15.856590160268947,
    "longitude": 104.02103511196691,
    "aqi": 93.44655724702798
  },
  {
    "label": "Yasothon, Thailand",
    "latitude": 15.84076052805111,
    "longitude": 104.22230727998551,
    "aqi": 121.2773890996264
  },
  {
    "label": "Yasothon, Thailand",
    "latitude": 15.75381798491683,
    "longitude": 104.1755973901185,
    "aqi": 116.04651711339196
  },
  {
    "label": "Yasothon, Thailand",
    "latitude": 15.852002852268347,
    "longitude": 104.0281365391061,
    "aqi": 199.77379630901012
  },
  {
    "label": "Yasothon, Thailand",
    "latitude": 15.91630399901324,
    "longitude": 104.19546012629284,
    "aqi": 110.68770804204948
  },
  {
    "label": "Yasothon, Thailand",
    "latitude": 15.83849619310366,
    "longitude": 104.2846102655994,
    "aqi": 194.4792292006932
  },
  {
    "label": "Yasothon, Thailand",
    "latitude": 15.963525740595214,
    "longitude": 104.17982046281328,
    "aqi": 54.43441212320026
  },
  {
    "label": "Yasothon, Thailand",
    "latitude": 15.634050799426246,
    "longitude": 104.17041510163874,
    "aqi": 111.277962475271
  },
  {
    "label": "Yasothon, Thailand",
    "latitude": 15.854919144870745,
    "longitude": 104.30625565107039,
    "aqi": 132.38624470882792
  },
  {
    "label": "Nakhon Pathom, Mueang Nakhon Pathom District, Thailand",
    "latitude": 13.690987036736951,
    "longitude": 99.99601149676572,
    "aqi": 47.78603825272494
  },
  {
    "label": "Nakhon Pathom, Mueang Nakhon Pathom District, Thailand",
    "latitude": 13.662878886908931,
    "longitude": 99.96996578582954,
    "aqi": 69.06190607328176
  },
  {
    "label": "Nakhon Pathom, Mueang Nakhon Pathom District, Thailand",
    "latitude": 13.667713485242542,
    "longitude": 99.98282034556146,
    "aqi": 57.511476814478414
  },
  {
    "label": "Nakhon Pathom, Mueang Nakhon Pathom District, Thailand",
    "latitude": 13.660324398830733,
    "longitude": 100.1229462437185,
    "aqi": 178.40191680502045
  },
  {
    "label": "Nakhon Pathom, Mueang Nakhon Pathom District, Thailand",
    "latitude": 13.746552311004168,
    "longitude": 100.1933993653489,
    "aqi": 157.06300650384256
  },
  {
    "label": "Nakhon Pathom, Mueang Nakhon Pathom District, Thailand",
    "latitude": 13.696379778391774,
    "longitude": 99.91224709087267,
    "aqi": 177.8578997153761
  },
  {
    "label": "Nakhon Pathom, Mueang Nakhon Pathom District, Thailand",
    "latitude": 13.859335190492176,
    "longitude": 100.0661506366391,
    "aqi": 107.7864713470243
  },
  {
    "label": "Nakhon Pathom, Mueang Nakhon Pathom District, Thailand",
    "latitude": 13.763223171499035,
    "longitude": 100.12090741535604,
    "aqi": 49.129130372927214
  },
  {
    "label": "Nakhon Pathom, Mueang Nakhon Pathom District, Thailand",
    "latitude": 13.960352361572182,
    "longitude": 100.13687134777645,
    "aqi": 21.471945624458158
  },
  {
    "label": "Nakhon Pathom, Mueang Nakhon Pathom District, Thailand",
    "latitude": 13.809636495860039,
    "longitude": 100.19672028285221,
    "aqi": 95.74359480381486
  },
  {
    "label": "Nakhon Pathom, Mueang Nakhon Pathom District, Thailand",
    "latitude": 13.872931128550926,
    "longitude": 100.09751375214387,
    "aqi": 112.27232134588021
  },
  {
    "label": "Nakhon Pathom, Mueang Nakhon Pathom District, Thailand",
    "latitude": 13.72769026733236,
    "longitude": 99.89223494420803,
    "aqi": 120.45970197429126
  },
  {
    "label": "Nakhon Pathom, Mueang Nakhon Pathom District, Thailand",
    "latitude": 13.860955200584467,
    "longitude": 100.13988779459687,
    "aqi": 110.63045122622344
  },
  {
    "label": "Nakhon Pathom, Mueang Nakhon Pathom District, Thailand",
    "latitude": 13.805173762346787,
    "longitude": 100.17295099358354,
    "aqi": 142.60437303323988
  },
  {
    "label": "Nakhon Pathom, Mueang Nakhon Pathom District, Thailand",
    "latitude": 13.729107496029394,
    "longitude": 99.92027637187897,
    "aqi": 206.79716650114173
  },
  {
    "label": "Nakhon Pathom, Mueang Nakhon Pathom District, Thailand",
    "latitude": 13.695635823280746,
    "longitude": 100.05381693076511,
    "aqi": 81.33123668798564
  },
  {
    "label": "Nakhon Pathom, Mueang Nakhon Pathom District, Thailand",
    "latitude": 13.655380120538862,
    "longitude": 100.08389955458763,
    "aqi": 101.63480324466006
  },
  {
    "label": "Nakhon Pathom, Mueang Nakhon Pathom District, Thailand",
    "latitude": 13.901384538629884,
    "longitude": 99.98297085099856,
    "aqi": 33.14683878224665
  },
  {
    "label": "Nakhon Pathom, Mueang Nakhon Pathom District, Thailand",
    "latitude": 13.879820350350675,
    "longitude": 100.04744721619633,
    "aqi": 100.75488806615532
  },
  {
    "label": "Nakhon Pathom, Mueang Nakhon Pathom District, Thailand",
    "latitude": 13.901313750455726,
    "longitude": 100.15790152643014,
    "aqi": 68.27137572042801
  },
  {
    "label": "Nakhon Pathom, Mueang Nakhon Pathom District, Thailand",
    "latitude": 13.932288961178015,
    "longitude": 100.07689532181783,
    "aqi": 74.45914991967457
  },
  {
    "label": "Nakhon Pathom, Mueang Nakhon Pathom District, Thailand",
    "latitude": 13.774516262637636,
    "longitude": 99.9207265384179,
    "aqi": 177.17499925841722
  },
  {
    "label": "Nakhon Pathom, Mueang Nakhon Pathom District, Thailand",
    "latitude": 13.742651747400897,
    "longitude": 100.00839906383443,
    "aqi": 22.742164152123692
  },
  {
    "label": "Nakhon Pathom, Mueang Nakhon Pathom District, Thailand",
    "latitude": 13.892009685617477,
    "longitude": 100.12855311221045,
    "aqi": 184.40085434234993
  },
  {
    "label": "Nakhon Pathom, Mueang Nakhon Pathom District, Thailand",
    "latitude": 13.926939283436452,
    "longitude": 100.01147911434619,
    "aqi": 108.79516500640041
  },
  {
    "label": "Chiang Mai, Mueang Chiang Mai District, Chiang Mai, Thailand",
    "latitude": 18.948076260958917,
    "longitude": 99.02657354452975,
    "aqi": 54.72369112037712
  },
  {
    "label": "Chiang Mai, Mueang Chiang Mai District, Chiang Mai, Thailand",
    "latitude": 18.753584656008464,
    "longitude": 98.94623129036162,
    "aqi": 39.39009225166384
  },
  {
    "label": "Chiang Mai, Mueang Chiang Mai District, Chiang Mai, Thailand",
    "latitude": 18.75214598637002,
    "longitude": 98.94527925172974,
    "aqi": 134.49749294951803
  },
  {
    "label": "Chiang Mai, Mueang Chiang Mai District, Chiang Mai, Thailand",
    "latitude": 18.77114673163022,
    "longitude": 99.06252065523033,
    "aqi": 201.57288816703442
  },
  {
    "label": "Chiang Mai, Mueang Chiang Mai District, Chiang Mai, Thailand",
    "latitude": 18.639508464523768,
    "longitude": 99.06913171636141,
    "aqi": 77.47407203857108
  },
  {
    "label": "Chiang Mai, Mueang Chiang Mai District, Chiang Mai, Thailand",
    "latitude": 18.8860272665326,
    "longitude": 98.87657646595457,
    "aqi": 158.69460856201573
  },
  {
    "label": "Chiang Mai, Mueang Chiang Mai District, Chiang Mai, Thailand",
    "latitude": 18.76000991505553,
    "longitude": 99.13066274148044,
    "aqi": 47.52696592456032
  },
  {
    "label": "Chiang Mai, Mueang Chiang Mai District, Chiang Mai, Thailand",
    "latitude": 18.82712299913213,
    "longitude": 98.81614886292886,
    "aqi": 201.9655520918012
  },
  {
    "label": "Chiang Mai, Mueang Chiang Mai District, Chiang Mai, Thailand",
    "latitude": 18.69014041888813,
    "longitude": 98.89556272121257,
    "aqi": 86.24115482870394
  },
  {
    "label": "Chiang Mai, Mueang Chiang Mai District, Chiang Mai, Thailand",
    "latitude": 18.823544411665484,
    "longitude": 99.06367094318108,
    "aqi": 124.05656126741447
  },
  {
    "label": "Chiang Mai, Mueang Chiang Mai District, Chiang Mai, Thailand",
    "latitude": 18.692925652723794,
    "longitude": 99.01715460384773,
    "aqi": 27.892498633897425
  },
  {
    "label": "Chiang Mai, Mueang Chiang Mai District, Chiang Mai, Thailand",
    "latitude": 18.655018033362484,
    "longitude": 98.94147335381595,
    "aqi": 65.03897682977245
  },
  {
    "label": "Chiang Mai, Mueang Chiang Mai District, Chiang Mai, Thailand",
    "latitude": 18.647235652035253,
    "longitude": 98.99116096703601,
    "aqi": 163.6755390277448
  },
  {
    "label": "Chiang Mai, Mueang Chiang Mai District, Chiang Mai, Thailand",
    "latitude": 18.811560194863663,
    "longitude": 98.9449039947503,
    "aqi": 149.5865184990975
  },
  {
    "label": "Chiang Mai, Mueang Chiang Mai District, Chiang Mai, Thailand",
    "latitude": 18.758768876481312,
    "longitude": 98.8337425389713,
    "aqi": 138.45317507545622
  },
  {
    "label": "Chiang Mai, Mueang Chiang Mai District, Chiang Mai, Thailand",
    "latitude": 18.853010040044662,
    "longitude": 99.01060604988413,
    "aqi": 30.150143415092572
  },
  {
    "label": "Chiang Mai, Mueang Chiang Mai District, Chiang Mai, Thailand",
    "latitude": 18.929954111458056,
    "longitude": 99.11071919182156,
    "aqi": 129.86153161286398
  },
  {
    "label": "Chiang Mai, Mueang Chiang Mai District, Chiang Mai, Thailand",
    "latitude": 18.637044540900558,
    "longitude": 98.92828823376614,
    "aqi": 94.48275576342968
  },
  {
    "label": "Chiang Mai, Mueang Chiang Mai District, Chiang Mai, Thailand",
    "latitude": 18.928338105264473,
    "longitude": 99.03044529967227,
    "aqi": 191.54282139081053
  },
  {
    "label": "Chiang Mai, Mueang Chiang Mai District, Chiang Mai, Thailand",
    "latitude": 18.81578952731629,
    "longitude": 98.95762785894351,
    "aqi": 113.73573484881513
  },
  {
    "label": "Chiang Mai, Mueang Chiang Mai District, Chiang Mai, Thailand",
    "latitude": 18.839080640714506,
    "longitude": 99.0027816970511,
    "aqi": 43.63944448553244
  },
  {
    "label": "Chiang Mai, Mueang Chiang Mai District, Chiang Mai, Thailand",
    "latitude": 18.936590218618004,
    "longitude": 99.09166337620464,
    "aqi": 149.9752551091096
  },
  {
    "label": "Chiang Mai, Mueang Chiang Mai District, Chiang Mai, Thailand",
    "latitude": 18.922316711923113,
    "longitude": 98.90055831418147,
    "aqi": 153.66340537753877
  },
  {
    "label": "Chiang Mai, Mueang Chiang Mai District, Chiang Mai, Thailand",
    "latitude": 18.846484248365606,
    "longitude": 98.96688601909061,
    "aqi": 75.67768757670933
  },
  {
    "label": "Chiang Mai, Mueang Chiang Mai District, Chiang Mai, Thailand",
    "latitude": 18.86524816707074,
    "longitude": 98.93448794696884,
    "aqi": 48.9555437686972
  },
  {
    "label": "Fairbanks, AK, USA",
    "latitude": 64.96208650328704,
    "longitude": -147.88973678071582,
    "aqi": 86.86754019234384
  },
  {
    "label": "Fairbanks, AK, USA",
    "latitude": 64.83523558677626,
    "longitude": -148.18231400942608,
    "aqi": 55.26159890074445
  },
  {
    "label": "Fairbanks, AK, USA",
    "latitude": 64.98865240412339,
    "longitude": -147.89144709235808,
    "aqi": 25.93523753683529
  },
  {
    "label": "Fairbanks, AK, USA",
    "latitude": 64.70054975533283,
    "longitude": -147.60347428186972,
    "aqi": 207.0528640803216
  },
  {
    "label": "Fairbanks, AK, USA",
    "latitude": 64.71703894595412,
    "longitude": -147.97236230021642,
    "aqi": 204.65058925153045
  },
  {
    "label": "Fairbanks, AK, USA",
    "latitude": 64.74207077434475,
    "longitude": -148.10854145441658,
    "aqi": 204.7150358551515
  },
  {
    "label": "Fairbanks, AK, USA",
    "latitude": 64.88501400586385,
    "longitude": -147.56648309313752,
    "aqi": 74.06602509923815
  },
  {
    "label": "Fairbanks, AK, USA",
    "latitude": 64.82568649707619,
    "longitude": -147.37959215771673,
    "aqi": 58.32042447089022
  },
  {
    "label": "Fairbanks, AK, USA",
    "latitude": 64.94028973990382,
    "longitude": -147.89406342634976,
    "aqi": 67.26048059299245
  },
  {
    "label": "Fairbanks, AK, USA",
    "latitude": 64.83077746176426,
    "longitude": -147.39173254764557,
    "aqi": 134.9385175256212
  },
  {
    "label": "Fairbanks, AK, USA",
    "latitude": 64.69950886930837,
    "longitude": -147.8964775109909,
    "aqi": 26.71245727199521
  },
  {
    "label": "Fairbanks, AK, USA",
    "latitude": 64.78602908277247,
    "longitude": -148.10182672735846,
    "aqi": 146.11681655105446
  },
  {
    "label": "Fairbanks, AK, USA",
    "latitude": 64.81649214575376,
    "longitude": -147.6390407406972,
    "aqi": 91.06056603146804
  },
  {
    "label": "Fairbanks, AK, USA",
    "latitude": 64.92783228799013,
    "longitude": -148.07659545726233,
    "aqi": 27.23905431642362
  },
  {
    "label": "Fairbanks, AK, USA",
    "latitude": 64.95912905511055,
    "longitude": -147.68672979088487,
    "aqi": 108.70060826826167
  },
  {
    "label": "Fairbanks, AK, USA",
    "latitude": 64.74756975838471,
    "longitude": -148.00800937474042,
    "aqi": 41.51455901053985
  },
  {
    "label": "Fairbanks, AK, USA",
    "latitude": 64.93413117387462,
    "longitude": -147.78925081531764,
    "aqi": 148.28183322636383
  },
  {
    "label": "Fairbanks, AK, USA",
    "latitude": 64.78945985682851,
    "longitude": -148.099524552958,
    "aqi": 73.64858404808234
  },
  {
    "label": "Fairbanks, AK, USA",
    "latitude": 64.83578104252953,
    "longitude": -147.56236088392913,
    "aqi": 200.55553720306912
  },
  {
    "label": "Fairbanks, AK, USA",
    "latitude": 65.00414949675236,
    "longitude": -147.78518941377794,
    "aqi": 120.69675399261797
  },
  {
    "label": "Fairbanks, AK, USA",
    "latitude": 64.82756633161985,
    "longitude": -147.75438654127717,
    "aqi": 126.40061020499188
  },
  {
    "label": "Fairbanks, AK, USA",
    "latitude": 64.86815474261765,
    "longitude": -147.69684686559336,
    "aqi": 103.14121752415437
  },
  {
    "label": "Fairbanks, AK, USA",
    "latitude": 64.71912581155152,
    "longitude": -148.0485942331964,
    "aqi": 133.7539382252499
  },
  {
    "label": "Fairbanks, AK, USA",
    "latitude": 64.80990549452467,
    "longitude": -148.17869712762132,
    "aqi": 145.47898548846746
  },
  {
    "label": "Fairbanks, AK, USA",
    "latitude": 64.73226832702807,
    "longitude": -147.57421868026108,
    "aqi": 37.026048974655694
  },
  {
    "label": "Nakhon Ratchasima, Thailand",
    "latitude": 15.026330967897811,
    "longitude": 102.23594634362138,
    "aqi": 120.01977936527639
  },
  {
    "label": "Nakhon Ratchasima, Thailand",
    "latitude": 14.892107324800635,
    "longitude": 101.94852771407363,
    "aqi": 65.3741115713305
  },
  {
    "label": "Nakhon Ratchasima, Thailand",
    "latitude": 14.874093287901614,
    "longitude": 102.05180300090811,
    "aqi": 194.84431969509862
  },
  {
    "label": "Nakhon Ratchasima, Thailand",
    "latitude": 15.039157303495477,
    "longitude": 101.92886587095474,
    "aqi": 181.9684199037215
  },
  {
    "label": "Nakhon Ratchasima, Thailand",
    "latitude": 14.959071556490963,
    "longitude": 102.0589436841837,
    "aqi": 194.1688550678425
  },
  {
    "label": "Nakhon Ratchasima, Thailand",
    "latitude": 14.850287432220163,
    "longitude": 102.15092202695241,
    "aqi": 84.875996765916
  },
  {
    "label": "Nakhon Ratchasima, Thailand",
    "latitude": 15.087159590899214,
    "longitude": 102.18650251043218,
    "aqi": 195.88650809822303
  },
  {
    "label": "Nakhon Ratchasima, Thailand",
    "latitude": 14.961433773532036,
    "longitude": 102.28281519848179,
    "aqi": 148.56681642848446
  },
  {
    "label": "Nakhon Ratchasima, Thailand",
    "latitude": 15.13135916722664,
    "longitude": 102.08912914234382,
    "aqi": 176.68612698263567
  },
  {
    "label": "Nakhon Ratchasima, Thailand",
    "latitude": 15.042025079271324,
    "longitude": 102.22626701449968,
    "aqi": 94.91361709875544
  },
  {
    "label": "Nakhon Ratchasima, Thailand",
    "latitude": 15.030009946570413,
    "longitude": 102.02846035646998,
    "aqi": 158.12644343247996
  },
  {
    "label": "Nakhon Ratchasima, Thailand",
    "latitude": 14.860368630628574,
    "longitude": 102.08433404120925,
    "aqi": 62.17331056002101
  },
  {
    "label": "Nakhon Ratchasima, Thailand",
    "latitude": 14.975049716968575,
    "longitude": 101.95713881201179,
    "aqi": 215.9476995234227
  },
  {
    "label": "Nakhon Ratchasima, Thailand",
    "latitude": 14.992239550528085,
    "longitude": 102.10007041167572,
    "aqi": 213.84348550514576
  },
  {
    "label": "Nakhon Ratchasima, Thailand",
    "latitude": 14.95469449662121,
    "longitude": 101.92205967678711,
    "aqi": 80.23665679336641
  },
  {
    "label": "Nakhon Ratchasima, Thailand",
    "latitude": 14.91219451069835,
    "longitude": 102.08586472108898,
    "aqi": 190.5328726340944
  },
  {
    "label": "Nakhon Ratchasima, Thailand",
    "latitude": 15.01425781738665,
    "longitude": 102.10369572051516,
    "aqi": 174.25191370297222
  },
  {
    "label": "Nakhon Ratchasima, Thailand",
    "latitude": 15.139839893754232,
    "longitude": 102.17157221852936,
    "aqi": 120.68994410177505
  },
  {
    "label": "Nakhon Ratchasima, Thailand",
    "latitude": 14.903729373585763,
    "longitude": 102.16204757576439,
    "aqi": 188.82758770649917
  },
  {
    "label": "Nakhon Ratchasima, Thailand",
    "latitude": 15.028272152053887,
    "longitude": 102.15044265606748,
    "aqi": 23.752429236269883
  },
  {
    "label": "Nakhon Ratchasima, Thailand",
    "latitude": 14.816270145269796,
    "longitude": 102.17394495798615,
    "aqi": 117.95718347915133
  },
  {
    "label": "Nakhon Ratchasima, Thailand",
    "latitude": 14.950338799834396,
    "longitude": 101.93583971999811,
    "aqi": 209.17939709096183
  },
  {
    "label": "Nakhon Ratchasima, Thailand",
    "latitude": 15.003262130007402,
    "longitude": 102.00819899269159,
    "aqi": 40.267476005643914
  },
  {
    "label": "Nakhon Ratchasima, Thailand",
    "latitude": 14.989491433118852,
    "longitude": 102.02881724790748,
    "aqi": 203.4267429161952
  },
  {
    "label": "Nakhon Ratchasima, Thailand",
    "latitude": 14.979292859201157,
    "longitude": 102.19557674301448,
    "aqi": 88.57581438787773
  },
  {
    "label": "Hai Ya, Chiang Mai City, Chiang Mai Province, Thailand",
    "latitude": 18.712147643254013,
    "longitude": 98.98293461707158,
    "aqi": 193.01069542342756
  },
  {
    "label": "Hai Ya, Chiang Mai City, Chiang Mai Province, Thailand",
    "latitude": 18.87303437121665,
    "longitude": 98.87723852714817,
    "aqi": 206.66856441206457
  },
  {
    "label": "Hai Ya, Chiang Mai City, Chiang Mai Province, Thailand",
    "latitude": 18.816561505160482,
    "longitude": 99.0708161312104,
    "aqi": 74.94178838646855
  },
  {
    "label": "Hai Ya, Chiang Mai City, Chiang Mai Province, Thailand",
    "latitude": 18.727960038060097,
    "longitude": 98.87550235031497,
    "aqi": 122.81890167479584
  },
  {
    "label": "Hai Ya, Chiang Mai City, Chiang Mai Province, Thailand",
    "latitude": 18.919345423083577,
    "longitude": 98.94120799434975,
    "aqi": 66.89760254615219
  },
  {
    "label": "Hai Ya, Chiang Mai City, Chiang Mai Province, Thailand",
    "latitude": 18.663789891862653,
    "longitude": 99.02638119765423,
    "aqi": 63.65097744887607
  },
  {
    "label": "Hai Ya, Chiang Mai City, Chiang Mai Province, Thailand",
    "latitude": 18.829083726299206,
    "longitude": 98.91162451904893,
    "aqi": 52.264009454927134
  },
  {
    "label": "Hai Ya, Chiang Mai City, Chiang Mai Province, Thailand",
    "latitude": 18.680489269185664,
    "longitude": 99.01307560216549,
    "aqi": 117.34143142176515
  },
  {
    "label": "Hai Ya, Chiang Mai City, Chiang Mai Province, Thailand",
    "latitude": 18.713144543587607,
    "longitude": 99.00466350793701,
    "aqi": 159.63958318303972
  },
  {
    "label": "Hai Ya, Chiang Mai City, Chiang Mai Province, Thailand",
    "latitude": 18.71133751376879,
    "longitude": 98.81892742850103,
    "aqi": 172.71527082429319
  },
  {
    "label": "Hai Ya, Chiang Mai City, Chiang Mai Province, Thailand",
    "latitude": 18.82316843641808,
    "longitude": 98.94020964831921,
    "aqi": 102.69263270367846
  },
  {
    "label": "Hai Ya, Chiang Mai City, Chiang Mai Province, Thailand",
    "latitude": 18.905605207297405,
    "longitude": 99.04399858646154,
    "aqi": 78.22663574115148
  },
  {
    "label": "Hai Ya, Chiang Mai City, Chiang Mai Province, Thailand",
    "latitude": 18.60133887502543,
    "longitude": 98.92615945190482,
    "aqi": 153.40943198476606
  },
  {
    "label": "Hai Ya, Chiang Mai City, Chiang Mai Province, Thailand",
    "latitude": 18.92432545459874,
    "longitude": 99.04680022138926,
    "aqi": 31.8129802846072
  },
  {
    "label": "Hai Ya, Chiang Mai City, Chiang Mai Province, Thailand",
    "latitude": 18.877815708193378,
    "longitude": 98.98933358551547,
    "aqi": 72.02709248241742
  },
  {
    "label": "Hai Ya, Chiang Mai City, Chiang Mai Province, Thailand",
    "latitude": 18.669432540437647,
    "longitude": 98.92087242313727,
    "aqi": 87.29524868452881
  },
  {
    "label": "Hai Ya, Chiang Mai City, Chiang Mai Province, Thailand",
    "latitude": 18.823636674285616,
    "longitude": 99.0076257138412,
    "aqi": 176.909967999998
  },
  {
    "label": "Hai Ya, Chiang Mai City, Chiang Mai Province, Thailand",
    "latitude": 18.647357312031406,
    "longitude": 98.86175707098312,
    "aqi": 135.1243916628033
  },
  {
    "label": "Hai Ya, Chiang Mai City, Chiang Mai Province, Thailand",
    "latitude": 18.748953384919883,
    "longitude": 99.07312703385084,
    "aqi": 138.16147532427146
  },
  {
    "label": "Hai Ya, Chiang Mai City, Chiang Mai Province, Thailand",
    "latitude": 18.830034701837626,
    "longitude": 98.97741621422345,
    "aqi": 27.728548716674098
  },
  {
    "label": "Hai Ya, Chiang Mai City, Chiang Mai Province, Thailand",
    "latitude": 18.600738627810383,
    "longitude": 98.98410411365877,
    "aqi": 59.23502841695496
  },
  {
    "label": "Hai Ya, Chiang Mai City, Chiang Mai Province, Thailand",
    "latitude": 18.761513510561954,
    "longitude": 98.8854988303231,
    "aqi": 32.10184935447649
  },
  {
    "label": "Hai Ya, Chiang Mai City, Chiang Mai Province, Thailand",
    "latitude": 18.878189078620224,
    "longitude": 99.00191701998281,
    "aqi": 82.67946175798741
  },
  {
    "label": "Hai Ya, Chiang Mai City, Chiang Mai Province, Thailand",
    "latitude": 18.67874708797545,
    "longitude": 99.0913908191142,
    "aqi": 129.1785184737126
  },
  {
    "label": "Hai Ya, Chiang Mai City, Chiang Mai Province, Thailand",
    "latitude": 18.62334786534267,
    "longitude": 98.91254454824445,
    "aqi": 141.61900731376824
  },
  {
    "label": "Khon Kaen, Mueang Khon Kaen District, Khon Kaen, Thailand",
    "latitude": 16.453648635551374,
    "longitude": 102.93489788733787,
    "aqi": 33.09062604287301
  },
  {
    "label": "Khon Kaen, Mueang Khon Kaen District, Khon Kaen, Thailand",
    "latitude": 16.368286195129766,
    "longitude": 102.9918282767417,
    "aqi": 117.77439594825825
  },
  {
    "label": "Khon Kaen, Mueang Khon Kaen District, Khon Kaen, Thailand",
    "latitude": 16.58537508393672,
    "longitude": 102.81729405737451,
    "aqi": 87.78499834125272
  },
  {
    "label": "Khon Kaen, Mueang Khon Kaen District, Khon Kaen, Thailand",
    "latitude": 16.48188623013861,
    "longitude": 102.85128024729565,
    "aqi": 208.44874074318886
  },
  {
    "label": "Khon Kaen, Mueang Khon Kaen District, Khon Kaen, Thailand",
    "latitude": 16.521948037651658,
    "longitude": 102.78907748813296,
    "aqi": 76.50512063408456
  },
  {
    "label": "Khon Kaen, Mueang Khon Kaen District, Khon Kaen, Thailand",
    "latitude": 16.480342480048,
    "longitude": 102.97698509979753,
    "aqi": 97.48510109329479
  },
  {
    "label": "Khon Kaen, Mueang Khon Kaen District, Khon Kaen, Thailand",
    "latitude": 16.373590271141534,
    "longitude": 102.82858090951615,
    "aqi": 57.60882861457597
  },
  {
    "label": "Khon Kaen, Mueang Khon Kaen District, Khon Kaen, Thailand",
    "latitude": 16.594177333075418,
    "longitude": 102.73955872017758,
    "aqi": 102.46184695306181
  },
  {
    "label": "Khon Kaen, Mueang Khon Kaen District, Khon Kaen, Thailand",
    "latitude": 16.44336940324088,
    "longitude": 102.99100188366356,
    "aqi": 149.41096664645318
  },
  {
    "label": "Khon Kaen, Mueang Khon Kaen District, Khon Kaen, Thailand",
    "latitude": 16.368893055283426,
    "longitude": 102.80112659899609,
    "aqi": 184.0777215517377
  },
  {
    "label": "Khon Kaen, Mueang Khon Kaen District, Khon Kaen, Thailand",
    "latitude": 16.371967479637153,
    "longitude": 102.71940836623138,
    "aqi": 81.0078249465476
  },
  {
    "label": "Khon Kaen, Mueang Khon Kaen District, Khon Kaen, Thailand",
    "latitude": 16.389814162732936,
    "longitude": 102.96984356519319,
    "aqi": 166.72582032492323
  },
  {
    "label": "Khon Kaen, Mueang Khon Kaen District, Khon Kaen, Thailand",
    "latitude": 16.30460197636541,
    "longitude": 102.82478075454593,
    "aqi": 191.21258018942802
  },
  {
    "label": "Khon Kaen, Mueang Khon Kaen District, Khon Kaen, Thailand",
    "latitude": 16.47437706422762,
    "longitude": 102.95338577056451,
    "aqi": 98.23882878944421
  },
  {
    "label": "Khon Kaen, Mueang Khon Kaen District, Khon Kaen, Thailand",
    "latitude": 16.38478747320462,
    "longitude": 102.94408213285845,
    "aqi": 137.4620494021474
  },
  {
    "label": "Khon Kaen, Mueang Khon Kaen District, Khon Kaen, Thailand",
    "latitude": 16.27230219336042,
    "longitude": 102.8620037517084,
    "aqi": 65.77060705109264
  },
  {
    "label": "Khon Kaen, Mueang Khon Kaen District, Khon Kaen, Thailand",
    "latitude": 16.353204776490177,
    "longitude": 102.84774311907765,
    "aqi": 54.64293733324042
  },
  {
    "label": "Khon Kaen, Mueang Khon Kaen District, Khon Kaen, Thailand",
    "latitude": 16.41164066475046,
    "longitude": 102.82836898671933,
    "aqi": 152.3733049706146
  },
  {
    "label": "Khon Kaen, Mueang Khon Kaen District, Khon Kaen, Thailand",
    "latitude": 16.521758326303683,
    "longitude": 102.95337031557229,
    "aqi": 102.57984891532021
  },
  {
    "label": "Khon Kaen, Mueang Khon Kaen District, Khon Kaen, Thailand",
    "latitude": 16.597000590257384,
    "longitude": 102.74984042208867,
    "aqi": 172.56042730783963
  },
  {
    "label": "Khon Kaen, Mueang Khon Kaen District, Khon Kaen, Thailand",
    "latitude": 16.28793884636939,
    "longitude": 102.81260601222029,
    "aqi": 138.24729885993304
  },
  {
    "label": "Khon Kaen, Mueang Khon Kaen District, Khon Kaen, Thailand",
    "latitude": 16.319920165850494,
    "longitude": 102.7320290386996,
    "aqi": 131.06277003471882
  },
  {
    "label": "Khon Kaen, Mueang Khon Kaen District, Khon Kaen, Thailand",
    "latitude": 16.566476898978877,
    "longitude": 102.94183126081093,
    "aqi": 89.99624075644206
  },
  {
    "label": "Khon Kaen, Mueang Khon Kaen District, Khon Kaen, Thailand",
    "latitude": 16.28025265236579,
    "longitude": 102.8409021835256,
    "aqi": 95.98336472930036
  },
  {
    "label": "Khon Kaen, Mueang Khon Kaen District, Khon Kaen, Thailand",
    "latitude": 16.266584659530814,
    "longitude": 102.8606865938446,
    "aqi": 84.39730657518798
  },
  {
    "label": "Chon Buri, Thailand",
    "latitude": 13.497110533360518,
    "longitude": 101.04767779444234,
    "aqi": 69.51959004674644
  },
  {
    "label": "Chon Buri, Thailand",
    "latitude": 13.444787756129006,
    "longitude": 101.05451437238469,
    "aqi": 78.7223690089674
  },
  {
    "label": "Chon Buri, Thailand",
    "latitude": 13.46893697845189,
    "longitude": 101.03790163992632,
    "aqi": 199.0252918349926
  },
  {
    "label": "Chon Buri, Thailand",
    "latitude": 13.474133980499063,
    "longitude": 100.93382890970983,
    "aqi": 207.61383358155132
  },
  {
    "label": "Chon Buri, Thailand",
    "latitude": 13.271575167821315,
    "longitude": 100.84887089119859,
    "aqi": 204.4656530996226
  },
  {
    "label": "Chon Buri, Thailand",
    "latitude": 13.465513383117312,
    "longitude": 101.07166344532688,
    "aqi": 20.35005944249629
  },
  {
    "label": "Chon Buri, Thailand",
    "latitude": 13.37157203840855,
    "longitude": 100.82031349342589,
    "aqi": 22.029799973861792
  },
  {
    "label": "Chon Buri, Thailand",
    "latitude": 13.262490570957329,
    "longitude": 101.015549431059,
    "aqi": 103.08668592249143
  },
  {
    "label": "Chon Buri, Thailand",
    "latitude": 13.38579566081149,
    "longitude": 101.04272209503797,
    "aqi": 182.27019427784822
  },
  {
    "label": "Chon Buri, Thailand",
    "latitude": 13.387688848655985,
    "longitude": 100.94492395514834,
    "aqi": 73.62702577912924
  },
  {
    "label": "Chon Buri, Thailand",
    "latitude": 13.293120529611528,
    "longitude": 100.83783375001224,
    "aqi": 73.41852597579866
  },
  {
    "label": "Chon Buri, Thailand",
    "latitude": 13.308296574735412,
    "longitude": 100.9564444313452,
    "aqi": 44.11150141629723
  },
  {
    "label": "Chon Buri, Thailand",
    "latitude": 13.484914342857799,
    "longitude": 100.9242882930101,
    "aqi": 60.87823244667601
  },
  {
    "label": "Chon Buri, Thailand",
    "latitude": 13.413464917624296,
    "longitude": 101.05838004166651,
    "aqi": 150.94102747508677
  },
  {
    "label": "Chon Buri, Thailand",
    "latitude": 13.430824804121581,
    "longitude": 100.96851359838098,
    "aqi": 90.52685137178716
  },
  {
    "label": "Chon Buri, Thailand",
    "latitude": 13.238567199615135,
    "longitude": 101.10854697639566,
    "aqi": 206.25932963162194
  },
  {
    "label": "Chon Buri, Thailand",
    "latitude": 13.352044188348682,
    "longitude": 100.99586267039243,
    "aqi": 77.5080895903861
  },
  {
    "label": "Chon Buri, Thailand",
    "latitude": 13.46127487709913,
    "longitude": 101.10475239001964,
    "aqi": 76.60397678050373
  },
  {
    "label": "Chon Buri, Thailand",
    "latitude": 13.400241403355507,
    "longitude": 100.9256171344003,
    "aqi": 151.4907063056371
  },
  {
    "label": "Chon Buri, Thailand",
    "latitude": 13.258023239645375,
    "longitude": 101.07060390541888,
    "aqi": 130.4348316947891
  },
  {
    "label": "Chon Buri, Thailand",
    "latitude": 13.45554373733997,
    "longitude": 101.01119756979296,
    "aqi": 112.85932124460525
  },
  {
    "label": "Chon Buri, Thailand",
    "latitude": 13.33668504728488,
    "longitude": 101.09180126113773,
    "aqi": 154.43652999834828
  },
  {
    "label": "Chon Buri, Thailand",
    "latitude": 13.43864040821734,
    "longitude": 100.89772130358782,
    "aqi": 107.00470383153056
  },
  {
    "label": "Chon Buri, Thailand",
    "latitude": 13.226951660027948,
    "longitude": 101.02593641678293,
    "aqi": 163.52419655386984
  },
  {
    "label": "Chon Buri, Thailand",
    "latitude": 13.477385796652447,
    "longitude": 101.11479395152911,
    "aqi": 137.30333281409668
  },
  {
    "label": "Chachoengsao, Thailand",
    "latitude": 13.851884838007052,
    "longitude": 101.10592100056873,
    "aqi": 36.598514370044185
  },
  {
    "label": "Chachoengsao, Thailand",
    "latitude": 13.604955499574265,
    "longitude": 101.11958873889529,
    "aqi": 65.22032832652845
  },
  {
    "label": "Chachoengsao, Thailand",
    "latitude": 13.833684085970932,
    "longitude": 101.1775946417929,
    "aqi": 147.9019500191514
  },
  {
    "label": "Chachoengsao, Thailand",
    "latitude": 13.81657377236632,
    "longitude": 101.12538596527313,
    "aqi": 139.65439248055657
  },
  {
    "label": "Chachoengsao, Thailand",
    "latitude": 13.751950078455351,
    "longitude": 101.22042147800106,
    "aqi": 91.95590910808289
  },
  {
    "label": "Chachoengsao, Thailand",
    "latitude": 13.835240002223559,
    "longitude": 100.99257584903447,
    "aqi": 27.78141007816915
  },
  {
    "label": "Chachoengsao, Thailand",
    "latitude": 13.660659010965855,
    "longitude": 100.99267505671779,
    "aqi": 55.26037408046019
  },
  {
    "label": "Chachoengsao, Thailand",
    "latitude": 13.710078428873755,
    "longitude": 100.9584941024608,
    "aqi": 123.34481671901936
  },
  {
    "label": "Chachoengsao, Thailand",
    "latitude": 13.820051487305072,
    "longitude": 101.12013035323004,
    "aqi": 123.32441100755219
  },
  {
    "label": "Chachoengsao, Thailand",
    "latitude": 13.855174616799482,
    "longitude": 101.13498148102586,
    "aqi": 184.74748374060243
  },
  {
    "label": "Chachoengsao, Thailand",
    "latitude": 13.779715654020107,
    "longitude": 101.13925453521435,
    "aqi": 144.50702028348962
  },
  {
    "label": "Chachoengsao, Thailand",
    "latitude": 13.7159102038132,
    "longitude": 100.98222287576905,
    "aqi": 200.35593984740535
  },
  {
    "label": "Chachoengsao, Thailand",
    "latitude": 13.77689434973915,
    "longitude": 100.9296828042666,
    "aqi": 32.8153283519131
  },
  {
    "label": "Chachoengsao, Thailand",
    "latitude": 13.67017829569113,
    "longitude": 101.01906259370048,
    "aqi": 29.073532858427093
  },
  {
    "label": "Chachoengsao, Thailand",
    "latitude": 13.519734345860211,
    "longitude": 101.04546367201067,
    "aqi": 180.0184616257582
  },
  {
    "label": "Chachoengsao, Thailand",
    "latitude": 13.702032504125482,
    "longitude": 101.1177078009833,
    "aqi": 200.6481542593826
  },
  {
    "label": "Chachoengsao, Thailand",
    "latitude": 13.630274411859586,
    "longitude": 100.97924649028322,
    "aqi": 37.806239767891796
  },
  {
    "label": "Chachoengsao, Thailand",
    "latitude": 13.600341958453317,
    "longitude": 101.14870939704551,
    "aqi": 187.79093445926105
  },
  {
    "label": "Chachoengsao, Thailand",
    "latitude": 13.741877302970929,
    "longitude": 101.17643414637158,
    "aqi": 25.9620795393295
  },
  {
    "label": "Chachoengsao, Thailand",
    "latitude": 13.761665940745925,
    "longitude": 101.1927404123833,
    "aqi": 115.54077902541889
  },
  {
    "label": "Chachoengsao, Thailand",
    "latitude": 13.55952847807411,
    "longitude": 101.09224408551528,
    "aqi": 176.56677131487572
  },
  {
    "label": "Chachoengsao, Thailand",
    "latitude": 13.713588051991048,
    "longitude": 101.05383098332828,
    "aqi": 49.590790519632826
  },
  {
    "label": "Chachoengsao, Thailand",
    "latitude": 13.581877623039373,
    "longitude": 101.2060403667159,
    "aqi": 59.900686409458075
  },
  {
    "label": "Chachoengsao, Thailand",
    "latitude": 13.66435715139427,
    "longitude": 101.20614103458627,
    "aqi": 198.39272849515285
  },
  {
    "label": "Chachoengsao, Thailand",
    "latitude": 13.759232453875482,
    "longitude": 101.22002882781118,
    "aqi": 24.1017074983146
  },
  {
    "label": "Bang Na, Bangkok, Thailand",
    "latitude": 13.800829267299646,
    "longitude": 100.51012658769399,
    "aqi": 203.5286589311313
  },
  {
    "label": "Bang Na, Bangkok, Thailand",
    "latitude": 13.727980405711353,
    "longitude": 100.6805305523872,
    "aqi": 121.96585944467262
  },
  {
    "label": "Bang Na, Bangkok, Thailand",
    "latitude": 13.759872188131862,
    "longitude": 100.54417861570361,
    "aqi": 136.23081515051203
  },
  {
    "label": "Bang Na, Bangkok, Thailand",
    "latitude": 13.573472945132355,
    "longitude": 100.7460123304121,
    "aqi": 92.59001577718149
  },
  {
    "label": "Bang Na, Bangkok, Thailand",
    "latitude": 13.71896166300364,
    "longitude": 100.56176741900448,
    "aqi": 25.4658521597704
  },
  {
    "label": "Bang Na, Bangkok, Thailand",
    "latitude": 13.756443022778692,
    "longitude": 100.50304453118264,
    "aqi": 148.18685428366305
  },
  {
    "label": "Bang Na, Bangkok, Thailand",
    "latitude": 13.648253546042813,
    "longitude": 100.75745674889733,
    "aqi": 159.3896814771065
  },
  {
    "label": "Bang Na, Bangkok, Thailand",
    "latitude": 13.782446232760439,
    "longitude": 100.6378659164307,
    "aqi": 54.135641406381765
  },
  {
    "label": "Bang Na, Bangkok, Thailand",
    "latitude": 13.78231643088288,
    "longitude": 100.5237760825255,
    "aqi": 65.33543257923225
  },
  {
    "label": "Bang Na, Bangkok, Thailand",
    "latitude": 13.620658774748062,
    "longitude": 100.56731454098744,
    "aqi": 148.84745810412323
  },
  {
    "label": "Bang Na, Bangkok, Thailand",
    "latitude": 13.70888939148397,
    "longitude": 100.4853456048553,
    "aqi": 59.1838800163848
  },
  {
    "label": "Bang Na, Bangkok, Thailand",
    "latitude": 13.749318860962001,
    "longitude": 100.57784689787907,
    "aqi": 96.11284644357656
  },
  {
    "label": "Bang Na, Bangkok, Thailand",
    "latitude": 13.802574067598567,
    "longitude": 100.70720095864128,
    "aqi": 45.03707327910072
  },
  {
    "label": "Bang Na, Bangkok, Thailand",
    "latitude": 13.67004758467194,
    "longitude": 100.7206763869486,
    "aqi": 22.4805162760686
  },
  {
    "label": "Bang Na, Bangkok, Thailand",
    "latitude": 13.763568025668599,
    "longitude": 100.67819630728945,
    "aqi": 162.69637834763108
  },
  {
    "label": "Bang Na, Bangkok, Thailand",
    "latitude": 13.77783316259305,
    "longitude": 100.62343703916996,
    "aqi": 105.85599006280886
  },
  {
    "label": "Bang Na, Bangkok, Thailand",
    "latitude": 13.710821857903317,
    "longitude": 100.55420548297595,
    "aqi": 25.13204223490127
  },
  {
    "label": "Bang Na, Bangkok, Thailand",
    "latitude": 13.833563728865512,
    "longitude": 100.5798854545901,
    "aqi": 60.76287738175903
  },
  {
    "label": "Bang Na, Bangkok, Thailand",
    "latitude": 13.554150781661214,
    "longitude": 100.54531540301478,
    "aqi": 204.36875638908305
  },
  {
    "label": "Bang Na, Bangkok, Thailand",
    "latitude": 13.669594126722576,
    "longitude": 100.72323710796563,
    "aqi": 186.12758782785568
  },
  {
    "label": "Bang Na, Bangkok, Thailand",
    "latitude": 13.548332940296046,
    "longitude": 100.65143008389754,
    "aqi": 209.48881871012495
  },
  {
    "label": "Bang Na, Bangkok, Thailand",
    "latitude": 13.659753268204446,
    "longitude": 100.49062767103034,
    "aqi": 53.55152885132604
  },
  {
    "label": "Bang Na, Bangkok, Thailand",
    "latitude": 13.634550883140928,
    "longitude": 100.44675415386399,
    "aqi": 62.1280940731358
  },
  {
    "label": "Bang Na, Bangkok, Thailand",
    "latitude": 13.65470225441784,
    "longitude": 100.79581524412707,
    "aqi": 24.918878229110966
  },
  {
    "label": "Bang Na, Bangkok, Thailand",
    "latitude": 13.752700256145241,
    "longitude": 100.76356295999199,
    "aqi": 219.89159588976116
  },
  {
    "label": "Phetchaburi, Thailand",
    "latitude": 12.997597062288047,
    "longitude": 100.07368880400867,
    "aqi": 191.0159946765362
  },
  {
    "label": "Phetchaburi, Thailand",
    "latitude": 13.092554173131106,
    "longitude": 99.9468431811243,
    "aqi": 193.78975559402852
  },
  {
    "label": "Phetchaburi, Thailand",
    "latitude": 13.28678062377759,
    "longitude": 99.92004547862732,
    "aqi": 195.8110559550392
  },
  {
    "label": "Phetchaburi, Thailand",
    "latitude": 12.996324350424167,
    "longitude": 100.03052610460975,
    "aqi": 51.07894446113937
  },
  {
    "label": "Phetchaburi, Thailand",
    "latitude": 13.10989885873336,
    "longitude": 99.92571756409593,
    "aqi": 66.98473219237735
  },
  {
    "label": "Phetchaburi, Thailand",
    "latitude": 12.941020778196993,
    "longitude": 99.92683877481763,
    "aqi": 219.97450404636754
  },
  {
    "label": "Phetchaburi, Thailand",
    "latitude": 13.174590169302363,
    "longitude": 99.91918208936785,
    "aqi": 36.16668150897587
  },
  {
    "label": "Phetchaburi, Thailand",
    "latitude": 13.215143735522592,
    "longitude": 100.0238438622704,
    "aqi": 25.31641166056125
  },
  {
    "label": "Phetchaburi, Thailand",
    "latitude": 12.986590125149311,
    "longitude": 100.00313919440345,
    "aqi": 97.19198614025164
  },
  {
    "label": "Phetchaburi, Thailand",
    "latitude": 13.214532288966474,
    "longitude": 99.90550083773954,
    "aqi": 62.42926509047882
  },
  {
    "label": "Phetchaburi, Thailand",
    "latitude": 13.087140901249747,
    "longitude": 99.89585639204036,
    "aqi": 112.77653982269918
  },
  {
    "label": "Phetchaburi, Thailand",
    "latitude": 13.190296074724383,
    "longitude": 99.81699206743531,
    "aqi": 169.92767410105307
  },
  {
    "label": "Phetchaburi, Thailand",
    "latitude": 13.042530248672815,
    "longitude": 99.82095530794898,
    "aqi": 107.67703389594072
  },
  {
    "label": "Phetchaburi, Thailand",
    "latitude": 13.093015213484557,
    "longitude": 99.95003839794585,
    "aqi": 181.69268080346816
  },
  {
    "label": "Phetchaburi, Thailand",
    "latitude": 13.076136167383115,
    "longitude": 99.75911819343536,
    "aqi": 146.552418887032
  },
  {
    "label": "Phetchaburi, Thailand",
    "latitude": 13.169872748969256,
    "longitude": 99.96528085032257,
    "aqi": 153.8368119223717
  },
  {
    "label": "Phetchaburi, Thailand",
    "latitude": 13.118347883184835,
    "longitude": 100.08887675759975,
    "aqi": 119.65808521704594
  },
  {
    "label": "Phetchaburi, Thailand",
    "latitude": 13.214747942244925,
    "longitude": 100.07965546340597,
    "aqi": 95.60286749764109
  },
  {
    "label": "Phetchaburi, Thailand",
    "latitude": 13.176663474615605,
    "longitude": 99.84500972556832,
    "aqi": 214.66270107952477
  },
  {
    "label": "Phetchaburi, Thailand",
    "latitude": 13.029685947130126,
    "longitude": 99.79540937412996,
    "aqi": 85.73764104790962
  },
  {
    "label": "Phetchaburi, Thailand",
    "latitude": 13.148464560741523,
    "longitude": 99.91398425608362,
    "aqi": 71.13867081576133
  },
  {
    "label": "Phetchaburi, Thailand",
    "latitude": 13.037123614820722,
    "longitude": 100.06673899446164,
    "aqi": 194.0955992615024
  },
  {
    "label": "Phetchaburi, Thailand",
    "latitude": 13.154687817895415,
    "longitude": 100.10232853843313,
    "aqi": 187.83891815619972
  },
  {
    "label": "Phetchaburi, Thailand",
    "latitude": 13.030527555247831,
    "longitude": 100.06119863519899,
    "aqi": 158.49797308671228
  },
  {
    "label": "Phetchaburi, Thailand",
    "latitude": 13.045037721779934,
    "longitude": 100.08211343070417,
    "aqi": 51.00689748011067
  },
  {
    "label": "Pattaya, Bang Lamung District, Chon Buri, Thailand",
    "latitude": 12.81513993075314,
    "longitude": 100.94992103928625,
    "aqi": 23.729776679477183
  },
  {
    "label": "Pattaya, Bang Lamung District, Chon Buri, Thailand",
    "latitude": 12.992364863055196,
    "longitude": 100.90747290576809,
    "aqi": 118.68782307398112
  },
  {
    "label": "Pattaya, Bang Lamung District, Chon Buri, Thailand",
    "latitude": 12.94395851585645,
    "longitude": 100.73262752598448,
    "aqi": 90.30421042114328
  },
  {
    "label": "Pattaya, Bang Lamung District, Chon Buri, Thailand",
    "latitude": 12.970743264839301,
    "longitude": 100.88740977431392,
    "aqi": 197.68826079450037
  },
  {
    "label": "Pattaya, Bang Lamung District, Chon Buri, Thailand",
    "latitude": 12.901002981065828,
    "longitude": 100.97251582486832,
    "aqi": 122.21849725893995
  },
  {
    "label": "Pattaya, Bang Lamung District, Chon Buri, Thailand",
    "latitude": 13.023859150723716,
    "longitude": 101.02339134310839,
    "aqi": 93.84758667301514
  },
  {
    "label": "Pattaya, Bang Lamung District, Chon Buri, Thailand",
    "latitude": 13.032790725142869,
    "longitude": 100.94263264339716,
    "aqi": 38.578206638412055
  },
  {
    "label": "Pattaya, Bang Lamung District, Chon Buri, Thailand",
    "latitude": 12.875072848825141,
    "longitude": 100.98411969542441,
    "aqi": 182.09389973805122
  },
  {
    "label": "Pattaya, Bang Lamung District, Chon Buri, Thailand",
    "latitude": 13.027172797677169,
    "longitude": 100.78817398233835,
    "aqi": 127.45210763692836
  },
  {
    "label": "Pattaya, Bang Lamung District, Chon Buri, Thailand",
    "latitude": 12.913726611335887,
    "longitude": 100.84662166503824,
    "aqi": 62.69486868032435
  },
  {
    "label": "Pattaya, Bang Lamung District, Chon Buri, Thailand",
    "latitude": 12.974438518499834,
    "longitude": 100.8731715577939,
    "aqi": 116.56041665125761
  },
  {
    "label": "Pattaya, Bang Lamung District, Chon Buri, Thailand",
    "latitude": 12.89161883627602,
    "longitude": 100.81044782307468,
    "aqi": 208.1409984313347
  },
  {
    "label": "Pattaya, Bang Lamung District, Chon Buri, Thailand",
    "latitude": 12.871286237214296,
    "longitude": 100.98189328818101,
    "aqi": 106.48771101995023
  },
  {
    "label": "Pattaya, Bang Lamung District, Chon Buri, Thailand",
    "latitude": 12.85159347036145,
    "longitude": 100.8209503829584,
    "aqi": 218.94292779388527
  },
  {
    "label": "Pattaya, Bang Lamung District, Chon Buri, Thailand",
    "latitude": 12.94049698509619,
    "longitude": 100.78428523546737,
    "aqi": 153.47452543933537
  },
  {
    "label": "Pattaya, Bang Lamung District, Chon Buri, Thailand",
    "latitude": 12.943246681463128,
    "longitude": 101.02471849721454,
    "aqi": 129.5171455534492
  },
  {
    "label": "Pattaya, Bang Lamung District, Chon Buri, Thailand",
    "latitude": 12.92217449914729,
    "longitude": 100.76859839096304,
    "aqi": 78.91356520726262
  },
  {
    "label": "Pattaya, Bang Lamung District, Chon Buri, Thailand",
    "latitude": 12.798842869150752,
    "longitude": 100.8697331077052,
    "aqi": 37.32697261776006
  },
  {
    "label": "Pattaya, Bang Lamung District, Chon Buri, Thailand",
    "latitude": 13.026382541930744,
    "longitude": 100.9006735352655,
    "aqi": 49.07437209128925
  },
  {
    "label": "Pattaya, Bang Lamung District, Chon Buri, Thailand",
    "latitude": 12.75990674318321,
    "longitude": 100.85742524954958,
    "aqi": 158.69688367682375
  },
  {
    "label": "Pattaya, Bang Lamung District, Chon Buri, Thailand",
    "latitude": 12.845873325533567,
    "longitude": 100.79103158669969,
    "aqi": 105.10533054296631
  },
  {
    "label": "Pattaya, Bang Lamung District, Chon Buri, Thailand",
    "latitude": 12.916012090514911,
    "longitude": 100.87232137401956,
    "aqi": 151.99686185149758
  },
  {
    "label": "Pattaya, Bang Lamung District, Chon Buri, Thailand",
    "latitude": 12.895660903064947,
    "longitude": 100.7810462859478,
    "aqi": 195.71781941651557
  },
  {
    "label": "Pattaya, Bang Lamung District, Chon Buri, Thailand",
    "latitude": 12.877915237773266,
    "longitude": 100.96594935505638,
    "aqi": 194.95857700776116
  },
  {
    "label": "Pattaya, Bang Lamung District, Chon Buri, Thailand",
    "latitude": 12.847485312342338,
    "longitude": 100.89279938419949,
    "aqi": 130.39199122693404
  },
  {
    "label": "Chiang Mai, Thailand",
    "latitude": 18.69370587314264,
    "longitude": 99.0629434835524,
    "aqi": 213.1605853219493
  },
  {
    "label": "Chiang Mai, Thailand",
    "latitude": 18.674269764915305,
    "longitude": 99.01792029151657,
    "aqi": 77.406197631239
  },
  {
    "label": "Chiang Mai, Thailand",
    "latitude": 18.664732371382918,
    "longitude": 98.88974595856594,
    "aqi": 173.35342422312377
  },
  {
    "label": "Chiang Mai, Thailand",
    "latitude": 18.93321737121718,
    "longitude": 98.945875415493,
    "aqi": 39.03989894537088
  },
  {
    "label": "Chiang Mai, Thailand",
    "latitude": 18.771302354608494,
    "longitude": 98.83912974061607,
    "aqi": 91.26248622104576
  },
  {
    "label": "Chiang Mai, Thailand",
    "latitude": 18.778606679092192,
    "longitude": 99.15790824997248,
    "aqi": 26.052585415216605
  },
  {
    "label": "Chiang Mai, Thailand",
    "latitude": 18.73136600043714,
    "longitude": 98.84880202567629,
    "aqi": 94.32040678271852
  },
  {
    "label": "Chiang Mai, Thailand",
    "latitude": 18.734879029962638,
    "longitude": 99.05376429368826,
    "aqi": 180.91225792318977
  },
  {
    "label": "Chiang Mai, Thailand",
    "latitude": 18.940697286577294,
    "longitude": 98.98251748067668,
    "aqi": 52.33454678343839
  },
  {
    "label": "Chiang Mai, Thailand",
    "latitude": 18.785586174264722,
    "longitude": 98.95523637404406,
    "aqi": 167.7162678891136
  },
  {
    "label": "Chiang Mai, Thailand",
    "latitude": 18.814842978298927,
    "longitude": 99.06294674924804,
    "aqi": 90.33504725341237
  },
  {
    "label": "Chiang Mai, Thailand",
    "latitude": 18.64433235355896,
    "longitude": 99.07213497091428,
    "aqi": 32.64869213606339
  },
  {
    "label": "Chiang Mai, Thailand",
    "latitude": 18.691220248980088,
    "longitude": 99.03582009228718,
    "aqi": 140.85166285488623
  },
  {
    "label": "Chiang Mai, Thailand",
    "latitude": 18.825455518784644,
    "longitude": 98.8361061359151,
    "aqi": 93.6701085578745
  },
  {
    "label": "Chiang Mai, Thailand",
    "latitude": 18.839164893583597,
    "longitude": 99.13854596927486,
    "aqi": 135.686514406725
  },
  {
    "label": "Chiang Mai, Thailand",
    "latitude": 18.755175954655996,
    "longitude": 98.84192222642412,
    "aqi": 49.55641714078525
  },
  {
    "label": "Chiang Mai, Thailand",
    "latitude": 18.667456248561,
    "longitude": 99.09359009847088,
    "aqi": 123.31063226138974
  },
  {
    "label": "Chiang Mai, Thailand",
    "latitude": 18.76992284338816,
    "longitude": 99.12400172574931,
    "aqi": 102.87131236054334
  },
  {
    "label": "Chiang Mai, Thailand",
    "latitude": 18.73680047773712,
    "longitude": 98.8836553257526,
    "aqi": 176.96762792722438
  },
  {
    "label": "Chiang Mai, Thailand",
    "latitude": 18.66719820374773,
    "longitude": 99.06335111613105,
    "aqi": 213.0378979874329
  },
  {
    "label": "Chiang Mai, Thailand",
    "latitude": 18.712654372405996,
    "longitude": 99.02194720070474,
    "aqi": 116.1198156326569
  },
  {
    "label": "Chiang Mai, Thailand",
    "latitude": 18.74907098685923,
    "longitude": 98.80597516766235,
    "aqi": 175.74200137880942
  },
  {
    "label": "Chiang Mai, Thailand",
    "latitude": 18.785138062796108,
    "longitude": 98.81429511918085,
    "aqi": 217.34930975697185
  },
  {
    "label": "Chiang Mai, Thailand",
    "latitude": 18.699026258291934,
    "longitude": 99.05169425358886,
    "aqi": 135.594687890166
  },
  {
    "label": "Chiang Mai, Thailand",
    "latitude": 18.80699259445785,
    "longitude": 98.87691839498716,
    "aqi": 102.07722162808881
  },
  {
    "label": "Bangkok,Thailand",
    "latitude": 13.617793794308975,
    "longitude": 100.46274982396987,
    "aqi": 33.62743616138707
  },
  {
    "label": "Bangkok,Thailand",
    "latitude": 13.79661873035437,
    "longitude": 100.57424908026843,
    "aqi": 84.4155175419371
  },
  {
    "label": "Bangkok,Thailand",
    "latitude": 13.72798552756008,
    "longitude": 100.55671039181057,
    "aqi": 52.265988963795024
  },
  {
    "label": "Bangkok,Thailand",
    "latitude": 13.796162399300774,
    "longitude": 100.38956117369125,
    "aqi": 165.81541043464279
  },
  {
    "label": "Bangkok,Thailand",
    "latitude": 13.679650685245967,
    "longitude": 100.53380348018987,
    "aqi": 142.57577828861753
  },
  {
    "label": "Bangkok,Thailand",
    "latitude": 13.83849789529618,
    "longitude": 100.58606215150274,
    "aqi": 79.97690211289446
  },
  {
    "label": "Bangkok,Thailand",
    "latitude": 13.722353436497231,
    "longitude": 100.63138816953995,
    "aqi": 191.77041932624505
  },
  {
    "label": "Bangkok,Thailand",
    "latitude": 13.856205488000953,
    "longitude": 100.49084877869434,
    "aqi": 51.18263324782306
  },
  {
    "label": "Bangkok,Thailand",
    "latitude": 13.810635158061233,
    "longitude": 100.66186026799504,
    "aqi": 80.41838202978593
  },
  {
    "label": "Bangkok,Thailand",
    "latitude": 13.84180261554383,
    "longitude": 100.44451777586256,
    "aqi": 37.183643027488095
  },
  {
    "label": "Bangkok,Thailand",
    "latitude": 13.900778124013733,
    "longitude": 100.55528820098901,
    "aqi": 197.12166877946677
  },
  {
    "label": "Bangkok,Thailand",
    "latitude": 13.874938511640972,
    "longitude": 100.56638903367912,
    "aqi": 197.15736547143894
  },
  {
    "label": "Bangkok,Thailand",
    "latitude": 13.66342179044729,
    "longitude": 100.51840654435942,
    "aqi": 144.62322033460617
  },
  {
    "label": "Bangkok,Thailand",
    "latitude": 13.841070886268405,
    "longitude": 100.48262902495635,
    "aqi": 85.53361753330842
  },
  {
    "label": "Bangkok,Thailand",
    "latitude": 13.797338779920928,
    "longitude": 100.53389930870024,
    "aqi": 194.26092509984778
  },
  {
    "label": "Bangkok,Thailand",
    "latitude": 13.69158641356069,
    "longitude": 100.41867667009791,
    "aqi": 158.66862067757114
  },
  {
    "label": "Bangkok,Thailand",
    "latitude": 13.662927561352644,
    "longitude": 100.5920164090214,
    "aqi": 160.07034594709555
  },
  {
    "label": "Bangkok,Thailand",
    "latitude": 13.678140594521444,
    "longitude": 100.37094332847497,
    "aqi": 168.3932779266924
  },
  {
    "label": "Bangkok,Thailand",
    "latitude": 13.73284234543888,
    "longitude": 100.59419158819684,
    "aqi": 52.839177955542894
  },
  {
    "label": "Bangkok,Thailand",
    "latitude": 13.86245233243999,
    "longitude": 100.5114901604319,
    "aqi": 102.50579881116904
  },
  {
    "label": "Bangkok,Thailand",
    "latitude": 13.579258086422128,
    "longitude": 100.47701334481134,
    "aqi": 181.58861686030582
  },
  {
    "label": "Bangkok,Thailand",
    "latitude": 13.727390163028424,
    "longitude": 100.44823348328109,
    "aqi": 175.6787780193468
  },
  {
    "label": "Bangkok,Thailand",
    "latitude": 13.667129188926166,
    "longitude": 100.67190119105898,
    "aqi": 214.20405494808057
  },
  {
    "label": "Bangkok,Thailand",
    "latitude": 13.773086843451164,
    "longitude": 100.52243586964033,
    "aqi": 77.78698152519848
  },
  {
    "label": "Bangkok,Thailand",
    "latitude": 13.620087511085993,
    "longitude": 100.61710374024435,
    "aqi": 177.91521536062993
  }
]